{
    "initial_capital": 1000000.0,
    "cash": 19.54375999986587,
    "holdings": {
        "600516": {
            "name": "方大炭素",
            "shares": 100,
            "buy_price": 6.82,
            "buy_date": "2026-03-05",
            "cost": 687.00682
        },
        "601179": {
            "name": "中国西电",
            "shares": 10400,
            "buy_price": 19.14,
            "buy_date": "2026-03-06",
            "cost": 199107.75456
        },
        "002001": {
            "name": "新和成",
            "shares": 5500,
            "buy_price": 36.1,
            "buy_date": "2026-03-06",
            "cost": 198601.62300000002
        },
        "000035": {
            "name": "中国天楹",
            "shares": 3600,
            "buy_price": 7.81,
            "buy_date": "2026-03-06",
            "cost": 28123.310159999997
        },
        "605117": {
            "name": "德业股份",
            "shares": 1200,
            "buy_price": 125.29,
            "buy_date": "2026-03-09",
            "cost": 150387.09048
        },
        "600406": {
            "name": "国电南瑞",
            "shares": 100,
            "buy_price": 31.48,
            "buy_date": "2026-03-09",
            "cost": 3153.03148
        },
        "601868": {
            "name": "中国能建",
            "shares": 64100,
            "buy_price": 3.12,
            "buy_date": "2026-03-10",
            "cost": 200043.99792
        },
        "300285": {
            "name": "国瓷材料",
            "shares": 4900,
            "buy_price": 38.02,
            "buy_date": "2026-03-10",
            "cost": 186346.43748000002
        },
        "688009": {
            "name": "中国通号",
            "shares": 200,
            "buy_price": 6.12,
            "buy_date": "2026-03-10",
            "cost": 1229.01224
        }
    },
    "history": [
        {
            "time": "2026-03-03 12:28:16",
            "action": "BUY",
            "code": "601872",
            "name": "招商轮船",
            "price": 19.65,
            "shares": 10100,
            "fees": 51.6009,
            "reason": "主升浪捕捉 (斜率:73.0°)"
        },
        {
            "time": "2026-03-03 12:28:16",
            "action": "BUY",
            "code": "002155",
            "name": "湖南黄金",
            "price": 43.01,
            "shares": 4600,
            "fees": 51.43996,
            "reason": "主升浪捕捉 (斜率:69.1°)"
        },
        {
            "time": "2026-03-03 12:28:16",
            "action": "BUY",
            "code": "600188",
            "name": "兖矿能源",
            "price": 20.14,
            "shares": 9900,
            "fees": 51.84036,
            "reason": "主升浪捕捉 (斜率:61.4°)"
        },
        {
            "time": "2026-03-03 12:28:16",
            "action": "BUY",
            "code": "605117",
            "name": "德业股份",
            "price": 125.52,
            "shares": 1500,
            "fees": 48.9528,
            "reason": "主升浪捕捉 (斜率:59.4°)"
        },
        {
            "time": "2026-03-03 12:28:16",
            "action": "BUY",
            "code": "601898",
            "name": "中煤能源",
            "price": 17.57,
            "shares": 11300,
            "fees": 51.62066,
            "reason": "主升浪捕捉 (斜率:55.3°)"
        },
        {
            "time": "2026-03-03 12:28:16",
            "action": "BUY",
            "code": "600938",
            "name": "中国海油",
            "price": 43.41,
            "shares": 300,
            "fees": 5.13023,
            "reason": "主升浪捕捉 (斜率:54.7°)"
        },
        {
            "time": "2026-03-03 12:28:16",
            "action": "BUY",
            "code": "600256",
            "name": "广汇能源",
            "price": 7.12,
            "shares": 500,
            "fees": 5.0356,
            "reason": "主升浪捕捉 (斜率:54.6°)"
        },
        {
            "time": "2026-03-03 12:28:16",
            "action": "BUY",
            "code": "601866",
            "name": "中远海发",
            "price": 3.17,
            "shares": 100,
            "fees": 5.00317,
            "reason": "主升浪捕捉 (斜率:42.8°)"
        },
        {
            "time": "2026-03-04 14:39:41",
            "action": "SELL",
            "code": "601872",
            "name": "招商轮船",
            "price": 18.22,
            "shares": 10100,
            "fees": 139.85672,
            "pnl": -14634.457620000001,
            "reason": "硬止损 (-7.3%)"
        },
        {
            "time": "2026-03-04 14:39:41",
            "action": "SELL",
            "code": "002155",
            "name": "湖南黄金",
            "price": 39.01,
            "shares": 4600,
            "fees": 136.37895999999998,
            "pnl": -18587.81892000002,
            "reason": "硬止损 (-9.3%)"
        },
        {
            "time": "2026-03-04 14:39:41",
            "action": "SELL",
            "code": "601866",
            "name": "中远海发",
            "price": 2.95,
            "shares": 100,
            "fees": 5.15045,
            "pnl": -32.15361999999999,
            "reason": "硬止损 (-6.9%)"
        },
        {
            "time": "2026-03-04 14:39:41",
            "action": "BUY",
            "code": "600875",
            "name": "东方电气",
            "price": 38.4,
            "shares": 5200,
            "fees": 51.9168,
            "reason": "主升浪捕捉 (斜率:62.6°)"
        },
        {
            "time": "2026-03-04 14:39:41",
            "action": "BUY",
            "code": "000988",
            "name": "华工科技",
            "price": 101.35,
            "shares": 1600,
            "fees": 42.1616,
            "reason": "主升浪捕捉 (斜率:55.3°)"
        },
        {
            "time": "2026-03-04 14:39:41",
            "action": "BUY",
            "code": "000998",
            "name": "隆平高科",
            "price": 11.01,
            "shares": 100,
            "fees": 5.01101,
            "reason": "主升浪捕捉 (斜率:36.1°)"
        },
        {
            "time": "2026-03-05 14:38:39",
            "action": "SELL",
            "code": "605117",
            "name": "德业股份",
            "price": 119.88,
            "shares": 1500,
            "fees": 136.66320000000002,
            "pnl": -8645.616000000009,
            "reason": "硬止损 (-4.5%)"
        },
        {
            "time": "2026-03-05 14:38:39",
            "action": "SELL",
            "code": "600256",
            "name": "广汇能源",
            "price": 6.83,
            "shares": 500,
            "fees": 6.74165,
            "pnl": -156.7772500000001,
            "reason": "硬止损 (-4.1%)"
        },
        {
            "time": "2026-03-05 14:38:39",
            "action": "SELL",
            "code": "000998",
            "name": "隆平高科",
            "price": 10.21,
            "shares": 100,
            "fees": 5.52071,
            "pnl": -90.53171999999984,
            "reason": "硬止损 (-7.3%)"
        },
        {
            "time": "2026-03-05 14:38:39",
            "action": "BUY",
            "code": "600026",
            "name": "中远海能",
            "price": 25.87,
            "shares": 7100,
            "fees": 47.75602,
            "reason": "主升浪捕捉 (斜率:70.7°)"
        },
        {
            "time": "2026-03-05 14:38:39",
            "action": "BUY",
            "code": "600516",
            "name": "方大炭素",
            "price": 6.82,
            "shares": 100,
            "fees": 5.00682,
            "reason": "主升浪捕捉 (斜率:31.1°)"
        },
        {
            "time": "2026-03-06 14:40:02",
            "action": "SELL",
            "code": "600938",
            "name": "中国海油",
            "price": 40.5,
            "shares": 300,
            "fees": 11.196499999999999,
            "pnl": -889.3267299999989,
            "reason": "硬止损 (-6.7%)"
        },
        {
            "time": "2026-03-06 14:40:02",
            "action": "SELL",
            "code": "600875",
            "name": "东方电气",
            "price": 44.21,
            "shares": 5200,
            "fees": 174.71792,
            "pnl": 29985.365279999998,
            "reason": "硬止盈 (+15.1%)"
        },
        {
            "time": "2026-03-06 14:40:02",
            "action": "SELL",
            "code": "000988",
            "name": "华工科技",
            "price": 114.83,
            "shares": 1600,
            "fees": 139.63327999999998,
            "pnl": 21386.20511999997,
            "reason": "硬止盈 (+13.3%)"
        },
        {
            "time": "2026-03-06 14:40:02",
            "action": "BUY",
            "code": "601179",
            "name": "中国西电",
            "price": 19.14,
            "shares": 10400,
            "fees": 51.754560000000005,
            "reason": "主升浪捕捉 (斜率:53.3°)"
        },
        {
            "time": "2026-03-06 14:40:02",
            "action": "BUY",
            "code": "002001",
            "name": "新和成",
            "price": 36.1,
            "shares": 5500,
            "fees": 51.623000000000005,
            "reason": "主升浪捕捉 (斜率:53.0°)"
        },
        {
            "time": "2026-03-06 14:40:02",
            "action": "BUY",
            "code": "000035",
            "name": "中国天楹",
            "price": 7.81,
            "shares": 3600,
            "fees": 7.31016,
            "reason": "主升浪捕捉 (斜率:51.9°)"
        },
        {
            "time": "2026-03-09 14:26:43",
            "action": "SELL",
            "code": "600026",
            "name": "中远海能",
            "price": 22.88,
            "shares": 7100,
            "fees": 123.46048000000002,
            "pnl": -21400.21650000001,
            "reason": "硬止损 (-11.6%)"
        },
        {
            "time": "2026-03-09 14:26:43",
            "action": "BUY",
            "code": "605117",
            "name": "德业股份",
            "price": 125.29,
            "shares": 1200,
            "fees": 39.09048000000001,
            "reason": "主升浪捕捉 (斜率:64.3°)"
        },
        {
            "time": "2026-03-09 14:26:43",
            "action": "BUY",
            "code": "600673",
            "name": "东阳光",
            "price": 40.35,
            "shares": 200,
            "fees": 5.0807,
            "reason": "主升浪捕捉 (斜率:61.9°)"
        },
        {
            "time": "2026-03-09 14:26:43",
            "action": "BUY",
            "code": "600406",
            "name": "国电南瑞",
            "price": 31.48,
            "shares": 100,
            "fees": 5.03148,
            "reason": "主升浪捕捉 (斜率:49.6°)"
        },
        {
            "time": "2026-03-10 14:28:33",
            "action": "SELL",
            "code": "600188",
            "name": "兖矿能源",
            "price": 19.28,
            "shares": 9900,
            "fees": 145.06271999999998,
            "pnl": -8710.90307999999,
            "reason": "硬止损 (-4.3%)"
        },
        {
            "time": "2026-03-10 14:28:33",
            "action": "SELL",
            "code": "601898",
            "name": "中煤能源",
            "price": 16.69,
            "shares": 11300,
            "fees": 143.33372,
            "pnl": -10138.954379999981,
            "reason": "硬止损 (-5.0%)"
        },
        {
            "time": "2026-03-10 14:28:33",
            "action": "SELL",
            "code": "600673",
            "name": "东阳光",
            "price": 38.49,
            "shares": 200,
            "fees": 8.925980000000001,
            "pnl": -386.0066800000004,
            "reason": "硬止损 (-4.6%)"
        },
        {
            "time": "2026-03-10 14:28:33",
            "action": "BUY",
            "code": "601868",
            "name": "中国能建",
            "price": 3.12,
            "shares": 64100,
            "fees": 51.99792,
            "reason": "主升浪捕捉 (斜率:55.1°)"
        },
        {
            "time": "2026-03-10 14:28:33",
            "action": "BUY",
            "code": "300285",
            "name": "国瓷材料",
            "price": 38.02,
            "shares": 4900,
            "fees": 48.43748000000001,
            "reason": "主升浪捕捉 (斜率:54.7°)"
        },
        {
            "time": "2026-03-10 14:28:33",
            "action": "BUY",
            "code": "688009",
            "name": "中国通号",
            "price": 6.12,
            "shares": 200,
            "fees": 5.01224,
            "reason": "主升浪捕捉 (斜率:30.9°)"
        }
    ]
}